siltsong/__about__.py
siltsong/__init__.py
siltsong/dust.py
siltsong/stars.py
siltsong/data/u39z010nt_drz.fits
siltsong/data/u39z010ot_drz.fits
siltsong/data/dust/extinction_efficiency_Draine_2011_fig_22.3.csv
siltsong/data/dust/scattering_efficiency_Draine_2011_fig_22.2.csv
siltsong/examples/M1-92.ipynb
siltsong/examples/MW.ipynb
siltsong/examples/.ipynb_checkpoints/M1-92-checkpoint.ipynb
siltsong/examples/.ipynb_checkpoints/MW-checkpoint.ipynb
siltsong-0.1.3.dist-info/METADATA
siltsong-0.1.3.dist-info/WHEEL
siltsong-0.1.3.dist-info/licenses/LICENSE
siltsong-0.1.3.dist-info/RECORD
